ariston_boiler_control/__init__.py
ariston_boiler_control/_boiler_control.py
ariston_boiler_control-0.0.4.dist-info/LICENSE
ariston_boiler_control-0.0.4.dist-info/METADATA
ariston_boiler_control-0.0.4.dist-info/WHEEL
ariston_boiler_control-0.0.4.dist-info/top_level.txt
ariston_boiler_control-0.0.4.dist-info/RECORD
