Metadata-Version: 2.1
Name: ariston-boiler-control
Version: 0.0.4
Summary: Managing ariston wifi boilers
Author: Francesco Santini
Author-email: francesco.santini@gmail.com
License: Apache License 2.0
Keywords: Smart home,boiler,ariston
Classifier: Programming Language :: Python :: 3
Requires-Python: >=3.7
License-File: LICENSE
Requires-Dist: requests
